CHANGES.txt
LICENSE.txt
MANIFEST.in
README.txt
TODO.txt
bootstrap.py
buildout.cfg
minify.cfg
setup.py
src/p01/__init__.py
src/p01.dashboard.egg-info/PKG-INFO
src/p01.dashboard.egg-info/SOURCES.txt
src/p01.dashboard.egg-info/dependency_links.txt
src/p01.dashboard.egg-info/entry_points.txt
src/p01.dashboard.egg-info/namespace_packages.txt
src/p01.dashboard.egg-info/not-zip-safe
src/p01.dashboard.egg-info/requires.txt
src/p01.dashboard.egg-info/top_level.txt
src/p01/dashboard/README.txt
src/p01/dashboard/__init__.py
src/p01/dashboard/configure.zcml
src/p01/dashboard/interfaces.py
src/p01/dashboard/layer.py
src/p01/dashboard/layer.zcml
src/p01/dashboard/permissions.zcml
src/p01/dashboard/processor.py
src/p01/dashboard/sampler.py
src/p01/dashboard/browser/__init__.py
src/p01/dashboard/browser/configure.zcml
src/p01/dashboard/browser/events.py
src/p01/dashboard/browser/events.zcml
src/p01/dashboard/browser/graphite.py
src/p01/dashboard/cdn/__init__.py
src/p01/dashboard/cdn/configure.zcml
src/p01/dashboard/cdn/css.zcml
src/p01/dashboard/cdn/font.zcml
src/p01/dashboard/cdn/js.zcml
src/p01/dashboard/cdn/min.zcml
src/p01/dashboard/cdn/css/p01.dashboard.css
src/p01/dashboard/cdn/font/FontAwesome.otf
src/p01/dashboard/cdn/font/fontawesome-webfont.eot
src/p01/dashboard/cdn/font/fontawesome-webfont.svg
src/p01/dashboard/cdn/font/fontawesome-webfont.ttf
src/p01/dashboard/cdn/font/fontawesome-webfont.woff
src/p01/dashboard/cdn/font/fontawesome-webfont.woff2
src/p01/dashboard/cdn/js/chart-2.4.0.js
src/p01/dashboard/cdn/js/chart.bundle-2.4.0.js
src/p01/dashboard/cdn/js/d3-3.5.17.js
src/p01/dashboard/cdn/js/eventsource-0.9.7.js
src/p01/dashboard/cdn/js/jquery-1.12.0.js
src/p01/dashboard/cdn/js/jquery.knob-1.2.13.js
src/p01/dashboard/cdn/js/jsface-2.4.8.js
src/p01/dashboard/cdn/js/justgauge-1.2.9.js
src/p01/dashboard/cdn/js/lodash-4.17.4.js
src/p01/dashboard/cdn/js/p01.dashboard.js
src/p01/dashboard/cdn/js/rickshaw-1.6.0.js
src/p01/dashboard/cdn/js/transparency-0.11.0.js
src/p01/dashboard/cdn/less/.xpp
src/p01/dashboard/cdn/less/core.less
src/p01/dashboard/cdn/less/font-awesome.less
src/p01/dashboard/cdn/less/grid.less
src/p01/dashboard/cdn/less/mixins.less
src/p01/dashboard/cdn/less/p01.dashboard.less
src/p01/dashboard/cdn/less/variables.less
src/p01/dashboard/cdn/less/zrt-replace.less
